LICENSE
MANIFEST.in
README.rst
requirements.txt
setup.py
webfinger.py
webfinger2.egg-info/PKG-INFO
webfinger2.egg-info/SOURCES.txt
webfinger2.egg-info/dependency_links.txt
webfinger2.egg-info/requires.txt
webfinger2.egg-info/top_level.txt