Metadata-Version: 1.1
Name: webfinger2
Version: 2.1
Summary: Simple Python implementation of WebFinger client protocol
Home-page: http://github.com/jcarbaugh/python-webfinger/
Author: Jeremy Carbaugh, Elizabeth Myers
Author-email: elizabeth@interlinked.me
License: BSD
Platform: any
Classifier: Development Status :: 5 - Production/Stable
Classifier: Intended Audience :: Developers
Classifier: License :: OSI Approved :: BSD License
Classifier: Operating System :: OS Independent
Classifier: Programming Language :: Python :: 3 :: Only
Classifier: Topic :: Software Development :: Libraries :: Python Modules
